Workbook

Sheet Assumptions
A1: Devorix — Financial Model (Assumptions)
A2: Blue = input you can change. Black = formula. All figures flagged; see Sources sheet.
A4: Parameter | B4: Value | C4: Unit / Note
A5: USD → INR | B5: =86 -> 86 | C5: assumption; verify spot rate
A6: Impressions per active dev / day | B6: =80 -> 80 | C6: ~20 prompts/hr x 4 hrs of AI coding (assumption)
A7: Active days / month | B7: =22 -> 22 | C7: working days (assumption)
A8: Gross eCPM (realized) | B8: =2 -> 2 | C8: USD. India est. Observed real: $0.27-$10.9; US blog est. $8-42 (see Sources)
A9: Dev revenue share | B9: =0.5 -> 0.5 | C9: match Kickbacks 50%; lever to 0.6-0.7 to beat rivals
A10: RazorpayX UPI payout cost | B10: =3 -> 3 | C10: INR per payout txn (Razorpay ~Rs2-5)
A11: Payout threshold | B11: =500 -> 500 | C11: INR; accrue then batch (keeps fee <1%)
A12: Infra cost / month | B12: =25000 -> 25000 | C12: INR; AWS/GCP Mumbai early (assumption)
A13: Team cost / month | B13: =200000 -> 200000 | C13: INR; lean founders + ~1 eng (assumption)
A14: Other opex / month | B14: =40000 -> 40000 | C14: INR; CA, legal, tools (assumption)

Sheet Monthly_Base
A1: Year-1 Monthly Projection (Base case)
A2: Active devs and fill-rate are blue inputs (a ramp). Fill-rate = % of impressions sold to real advertisers.
A4: Month | B4: 1 | C4: 2 | D4: 3 | E4: 4 | F4: 5 | G4: 6 | H4: 7 | I4: 8 | J4: 9 | K4: 10 | L4: 11 | M4: 12
A5: Active devs (EOM) | B5: 500 | C5: 1500 | D5: 4000 | E5: 8000 | F5: 13000 | G5: 20000 | H5: 28000 | I5: 38000 | J5: 50000 | K5: 65000 | L5: 82000 | M5: 100000
A6: Fill rate | B6: 0.02 | C6: 0.05 | D6: 0.1 | E6: 0.15 | F6: 0.2 | G6: 0.25 | H6: 0.3 | I6: 0.35 | J6: 0.4 | K6: 0.45 | L6: 0.5 | M6: 0.55
A7: Impressions/mo | B7: =B5*Assumptions!$B$6*Assumptions!$B$7 -> 880000 | C7: =C5*Assumptions!$B$6*Assumptions!$B$7 -> 2640000 | D7: =D5*Assumptions!$B$6*Assumptions!$B$7 -> 7040000 | E7: =E5*Assumptions!$B$6*Assumptions!$B$7 -> 14080000 | F7: =F5*Assumptions!$B$6*Assumptions!$B$7 -> 22880000 | G7: =G5*Assumptions!$B$6*Assumptions!$B$7 -> 35200000 | H7: =H5*Assumptions!$B$6*Assumptions!$B$7 -> 49280000 | I7: =I5*Assumptions!$B$6*Assumptions!$B$7 -> 66880000 | ... M7: =M5*Assumptions!$B$6*Assumptions!$B$7 -> 176000000
A8: Filled impressions | B8: =B7*B6 -> 17600 | C8: =C7*C6 -> 132000 | D8: =D7*D6 -> 704000 | E8: =E7*E6 -> 2112000 | F8: =F7*F6 -> 4576000 | G8: =G7*G6 -> 8800000 | H8: =H7*H6 -> 14784000 | I8: =I7*I6 -> 23408000 | ... M8: =M7*M6 -> 96800000
A9: Gross revenue (Rs) | B9: =B8/1000*Assumptions!$B$8*Assumptions!$B$5 -> 3027.2 | C9: =C8/1000*Assumptions!$B$8*Assumptions!$B$5 -> 22704 | D9: =D8/1000*Assumptions!$B$8*Assumptions!$B$5 -> 121088 | E9: =E8/1000*Assumptions!$B$8*Assumptions!$B$5 -> 363264 | F9: =F8/1000*Assumptions!$B$8*Assumptions!$B$5 -> 787072 | G9: =G8/1000*Assumptions!$B$8*Assumptions!$B$5 -> 1513600 | H9: =H8/1000*Assumptions!$B$8*Assumptions!$B$5 -> 2542848 | I9: =I8/1000*Assumptions!$B$8*Assumptions!$B$5 -> 4026176 | ... M9: =M8/1000*Assumptions!$B$8*Assumptions!$B$5 -> 16649600
A10: Dev payout (Rs) | B10: =B9*Assumptions!$B$9 -> 1513.6 | C10: =C9*Assumptions!$B$9 -> 11352 | D10: =D9*Assumptions!$B$9 -> 60544 | E10: =E9*Assumptions!$B$9 -> 181632 | F10: =F9*Assumptions!$B$9 -> 393536 | G10: =G9*Assumptions!$B$9 -> 756800 | H10: =H9*Assumptions!$B$9 -> 1271424 | I10: =I9*Assumptions!$B$9 -> 2013088 | ... M10: =M9*Assumptions!$B$9 -> 8324800
A11: Platform margin (Rs) | B11: =B9*(1-Assumptions!$B$9) -> 1513.6 | C11: =C9*(1-Assumptions!$B$9) -> 11352 | D11: =D9*(1-Assumptions!$B$9) -> 60544 | E11: =E9*(1-Assumptions!$B$9) -> 181632 | F11: =F9*(1-Assumptions!$B$9) -> 393536 | G11: =G9*(1-Assumptions!$B$9) -> 756800 | H11: =H9*(1-Assumptions!$B$9) -> 1271424 | I11: =I9*(1-Assumptions!$B$9) -> 2013088 | ... M11: =M9*(1-Assumptions!$B$9) -> 8324800
A12: Payout txn cost (Rs) | B12: =IF(B10=0,0,B10/Assumptions!$B$11*Assumptions!$B$10) -> 9.0816 | C12: =IF(C10=0,0,C10/Assumptions!$B$11*Assumptions!$B$10) -> 68.112 | D12: =IF(D10=0,0,D10/Assumptions!$B$11*Assumptions!$B$10) -> 363.264 | E12: =IF(E10=0,0,E10/Assumptions!$B$11*Assumptions!$B$10) -> 1089.792 | F12: =IF(F10=0,0,F10/Assumptions!$B$11*Assumptions!$B$10) -> 2361.216 | G12: =IF(G10=0,0,G10/Assumptions!$B$11*Assumptions!$B$10) -> 4540.8 | H12: =IF(H10=0,0,H10/Assumptions!$B$11*Assumptions!$B$10) -> 7628.544 | I12: =IF(I10=0,0,I10/Assumptions!$B$11*Assumptions!$B$10) -> 12078.528 | ... M12: =IF(M10=0,0,M10/Assumptions!$B$11*Assumptions!$B$10) -> 49948.8
A13: Opex (Rs) | B13: =Assumptions!$B$12+Assumptions!$B$13+Assumptions!$B$14 -> 265000 | C13: =Assumptions!$B$12+Assumptions!$B$13+Assumptions!$B$14 -> 265000 | D13: =Assumptions!$B$12+Assumptions!$B$13+Assumptions!$B$14 -> 265000 | E13: =Assumptions!$B$12+Assumptions!$B$13+Assumptions!$B$14 -> 265000 | F13: =Assumptions!$B$12+Assumptions!$B$13+Assumptions!$B$14 -> 265000 | G13: =Assumptions!$B$12+Assumptions!$B$13+Assumptions!$B$14 -> 265000 | H13: =Assumptions!$B$12+Assumptions!$B$13+Assumptions!$B$14 -> 265000 | I13: =Assumptions!$B$12+Assumptions!$B$13+Assumptions!$B$14 -> 265000 | ... M13: =Assumptions!$B$12+Assumptions!$B$13+Assumptions!$B$14 -> 265000
A14: Net profit (Rs) | B14: =B11-B12-B13 -> -263495.48 | C14: =C11-C12-C13 -> -253716.11 | D14: =D11-D12-D13 -> -204819.26 | E14: =E11-E12-E13 -> -84457.792 | F14: =F11-F12-F13 -> 126174.78 | G14: =G11-G12-G13 -> 487259.2 | H14: =H11-H12-H13 -> 998795.46 | I14: =I11-I12-I13 -> 1736009.5 | ... M14: =M11-M12-M13 -> 8009851.2
A15: Cumulative net (Rs) | B15: =B14 -> -263495.48 | C15: =B15+C14 -> -517211.59 | D15: =C15+D14 -> -722030.86 | E15: =D15+E14 -> -806488.65 | F15: =E15+F14 -> -680313.87 | G15: =F15+G14 -> -193054.67 | H15: =G15+H14 -> 805740.79 | I15: =H15+I14 -> 2541750.3 | J15: =I15+J14 -> 5285787.1 | ... M15: =L15+M14 -> 23334880

Sheet Scenarios
A1: Steady-state sensitivity (at a given active-dev base, full fill)
A2: Monthly platform NET margin (Rs lakh) BEFORE opex, = gross x (1 - dev share). Vary eCPM x devs.
A4: Active devs \ eCPM (USD) | B4: Conservative $0.8 | C4: Base $2.0 | D4: Optimistic $5.0
A5: 1000 | B5: =A5*Assumptions!$B$6*Assumptions!$B$7/1000*0.8*Assumptions!$B$5*(1-Assumptions!$B$9)/100000 -> 0.60544 | C5: =A5*Assumptions!$B$6*Assumptions!$B$7/1000*2*Assumptions!$B$5*(1-Assumptions!$B$9)/100000 -> 1.5136 | D5: =A5*Assumptions!$B$6*Assumptions!$B$7/1000*5*Assumptions!$B$5*(1-Assumptions!$B$9)/100000 -> 3.784
A6: 10000 | B6: =A6*Assumptions!$B$6*Assumptions!$B$7/1000*0.8*Assumptions!$B$5*(1-Assumptions!$B$9)/100000 -> 6.0544 | C6: =A6*Assumptions!$B$6*Assumptions!$B$7/1000*2*Assumptions!$B$5*(1-Assumptions!$B$9)/100000 -> 15.136 | D6: =A6*Assumptions!$B$6*Assumptions!$B$7/1000*5*Assumptions!$B$5*(1-Assumptions!$B$9)/100000 -> 37.84
A7: 50000 | B7: =A7*Assumptions!$B$6*Assumptions!$B$7/1000*0.8*Assumptions!$B$5*(1-Assumptions!$B$9)/100000 -> 30.272 | C7: =A7*Assumptions!$B$6*Assumptions!$B$7/1000*2*Assumptions!$B$5*(1-Assumptions!$B$9)/100000 -> 75.68 | D7: =A7*Assumptions!$B$6*Assumptions!$B$7/1000*5*Assumptions!$B$5*(1-Assumptions!$B$9)/100000 -> 189.2
A8: 100000 | B8: =A8*Assumptions!$B$6*Assumptions!$B$7/1000*0.8*Assumptions!$B$5*(1-Assumptions!$B$9)/100000 -> 60.544 | C8: =A8*Assumptions!$B$6*Assumptions!$B$7/1000*2*Assumptions!$B$5*(1-Assumptions!$B$9)/100000 -> 151.36 | D8: =A8*Assumptions!$B$6*Assumptions!$B$7/1000*5*Assumptions!$B$5*(1-Assumptions!$B$9)/100000 -> 378.4
A9: 200000 | B9: =A9*Assumptions!$B$6*Assumptions!$B$7/1000*0.8*Assumptions!$B$5*(1-Assumptions!$B$9)/100000 -> 121.088 | C9: =A9*Assumptions!$B$6*Assumptions!$B$7/1000*2*Assumptions!$B$5*(1-Assumptions!$B$9)/100000 -> 302.72 | D9: =A9*Assumptions!$B$6*Assumptions!$B$7/1000*5*Assumptions!$B$5*(1-Assumptions!$B$9)/100000 -> 756.8
A12: Per-dev economics / month (Rs)
A13: eCPM (USD) | B13: Gross/dev | C13: Dev keeps | D13: Platform keeps
A14: 0.8 | B14: =Assumptions!$B$6*Assumptions!$B$7/1000*A14*Assumptions!$B$5 -> 121.088 | C14: =B14*Assumptions!$B$9 -> 60.544 | D14: =B14*(1-Assumptions!$B$9) -> 60.544
A15: 2 | B15: =Assumptions!$B$6*Assumptions!$B$7/1000*A15*Assumptions!$B$5 -> 302.72 | C15: =B15*Assumptions!$B$9 -> 151.36 | D15: =B15*(1-Assumptions!$B$9) -> 151.36
A16: 5 | B16: =Assumptions!$B$6*Assumptions!$B$7/1000*A16*Assumptions!$B$5 -> 756.8 | C16: =B16*Assumptions!$B$9 -> 378.4 | D16: =B16*(1-Assumptions!$B$9) -> 378.4

Sheet Sources_Confidence
A1: Sources & Confidence (fact-check log)
A3: Figure | B3: Value used | C3: Source | D3: Confidence
A4: India GitHub developers 2026 | B4: 27 million | C4: GitHub via VARINDIA / InvestmentGuru, 2026 | D4: High (multi-source)
A5: India devs projected 2030 | B5: 57.5 million | C5: GitHub projection via press, 2026 | D5: Medium (projection)
A6: Kickbacks dev rev share | B6: 50% | C6: kickbacks.ai / GitHub repo | D6: High
A7: IdleAds rev share | B7: 70% | C7: idleads.dev; HN | D7: High
A8: Idlen rev share / CPM | B8: 70% / $20-42 | C8: idlen.io; dev.to AIWaitIndex | D8: Low (blog estimate)
A9: Observed real eCPM (HN tester) | B9: ~$10.9 ($4.43/407 impr) | C9: Hacker News tester report | D9: Low (single self-report)
A10: Observed real eCPM (PH bad day) | B10: ~$0.27 | C10: Product Hunt reviewer | D10: Low (single self-report)
A11: Blog CPM range | B11: $8-42 | C11: dev.to AIWaitIndex (one blogger) | D11: Low (unverified estimate)
A12: eCPM used in model (India) | B12: $2.0 base | C12: Our conservative assumption | D12: Assumption
A13: RazorpayX UPI payout cost | B13: Rs 2-5 | C13: Razorpay docs / productgrowth.in | D13: High
A14: USD-INR | B14: 86 | C14: Assumption; verify spot | D14: Assumption
A15: Impr/dev/day, active days, opex | B15: 80 / 22 / lean | C15: Our assumptions | D15: Assumption
