Workbook

Sheet Assumptions
A1: Devorix — REALISTIC Financial Model
A2: Grounded in verified data (June 2026). Blue=input. All figures tagged in Sources sheet. Constraints: <=500 users in 4 mo, <=Rs1L budget, 1-2 advertisers in 14 days.
A4: Parameter | B4: Value | C4: Note / Source
A5: USD -> INR | B5: =94.5 -> 94.5 | C5: VERIFIED spot Jun 2026 (exchange-rates.org)
A6: Installs (end of month 4, cap) | B6: =500 -> 500 | C6: Founder constraint
A7: Weekly-active rate | B7: =0.4 -> 0.4 | C7: assumption (ad-averse devs; many install, few keep)
A8: Impressions / active dev / day | B8: =80 -> 80 | C8: ~20 prompts/hr x 4 hrs (assumption)
A9: Active days / month | B9: =22 -> 22 | C9: assumption
A10: Realistic GROSS eCPM (USD) | B10: =1 -> 1 | C10: VERIFIED real range $0.27-$11; steady-state ~$0.27. Use $0.5-$2.
A11: Dev revenue share | B11: =0.5 -> 0.5 | C11: Kickbacks 50% / IdleAds 70%; decided 50%
A12: Flat sponsorship fee / advertiser / mo (Rs) | B12: =15000 -> 15000 | C12: PLAN: direct deal, not CPM. Pilot-level (assumption)
A13: Payout cost / txn (Rs) | B13: =4 -> 4 | C13: RazorpayX UPI Rs2-5 +GST (verified)
A14: Payout threshold (Rs) | B14: =500 -> 500 | C14: accrue+batch
A15: Infra + Gemini API / mo (Rs) | B15: =3000 -> 3000 | C15: Vercel/Render + Gemini for AI tools (assumption)
A16: Misc / mo (Rs) | B16: =2000 -> 2000 | C16: domain, tools (assumption)
A17: Founder salary / mo (Rs) | B17: =0 -> 0 | C17: solo, sweat equity = low burn
A18: Total cash available (Rs) | B18: =100000 -> 100000 | C18: Founder constraint

Sheet Reality_Check_CPM
A1: Reality check: programmatic CPM at 500 users earns almost nothing
A2: This proves WHY the plan uses flat advertiser deals, not CPM, at small scale.
A4: Metric | B4: Value
A5: Installs | B5: 500
A6: Active devs (installs x WAU) | B6: =B5*Assumptions!$B$7 -> 200
A7: Impressions / mo | B7: =B6*Assumptions!$B$8*Assumptions!$B$9 -> 352000
A8: Gross / mo @100% fill (Rs) | B8: =B7/1000*Assumptions!$B$10*Assumptions!$B$5 -> 33264
A9: Gross / mo @15% realistic fill (Rs) | B9: =B8*0.15 -> 4989.6
A10: Dev share of realistic (Rs) | B10: =B9*Assumptions!$B$11 -> 2494.8
A11: Per active dev / mo (Rs) | B11: =IF(B6=0,0,B10/B6) -> 12.474
A13: Takeaway: at 500 users, CPM yields a few hundred rupees/month total. Unviable. -> sell flat sponsorships.

Sheet Plan_4mo_FlatDeals
A1: 4-Month Plan — flat sponsorship deals (the realistic path)
A4: Metric | B4: Month 1 | C4: Month 2 | D4: Month 3 | E4: Month 4
A5: Installs (cumulative) | B5: 100 | C5: 250 | D5: 400 | E5: 500
A6: Active devs | B6: =B5*Assumptions!$B$7 -> 40 | C6: =C5*Assumptions!$B$7 -> 100 | D6: =D5*Assumptions!$B$7 -> 160 | E6: =E5*Assumptions!$B$7 -> 200
A7: # Advertisers (flat deals) | B7: 1 | C7: 2 | D7: 2 | E7: 3
A8: Gross revenue (Rs) | B8: =B7*Assumptions!$B$12 -> 15000 | C8: =C7*Assumptions!$B$12 -> 30000 | D8: =D7*Assumptions!$B$12 -> 30000 | E8: =E7*Assumptions!$B$12 -> 45000
A9: Dev payout pool (Rs) | B9: =B8*Assumptions!$B$11 -> 7500 | C9: =C8*Assumptions!$B$11 -> 15000 | D9: =D8*Assumptions!$B$11 -> 15000 | E9: =E8*Assumptions!$B$11 -> 22500
A10: Platform margin (Rs) | B10: =B8*(1-Assumptions!$B$11) -> 7500 | C10: =C8*(1-Assumptions!$B$11) -> 15000 | D10: =D8*(1-Assumptions!$B$11) -> 15000 | E10: =E8*(1-Assumptions!$B$11) -> 22500
A11: Payout txn cost (Rs) | B11: =IF(B9=0,0,B9/Assumptions!$B$14*Assumptions!$B$13) -> 60 | C11: =IF(C9=0,0,C9/Assumptions!$B$14*Assumptions!$B$13) -> 120 | D11: =IF(D9=0,0,D9/Assumptions!$B$14*Assumptions!$B$13) -> 120 | E11: =IF(E9=0,0,E9/Assumptions!$B$14*Assumptions!$B$13) -> 180
A12: Infra+Gemini (Rs) | B12: =Assumptions!$B$15 -> 3000 | C12: =Assumptions!$B$15 -> 3000 | D12: =Assumptions!$B$15 -> 3000 | E12: =Assumptions!$B$15 -> 3000
A13: Misc (Rs) | B13: =Assumptions!$B$16 -> 2000 | C13: =Assumptions!$B$16 -> 2000 | D13: =Assumptions!$B$16 -> 2000 | E13: =Assumptions!$B$16 -> 2000
A14: Founder salary (Rs) | B14: =Assumptions!$B$17 -> 0 | C14: =Assumptions!$B$17 -> 0 | D14: =Assumptions!$B$17 -> 0 | E14: =Assumptions!$B$17 -> 0
A15: Total costs (Rs) | B15: =B11+B12+B13+B14 -> 5060 | C15: =C11+C12+C13+C14 -> 5120 | D15: =D11+D12+D13+D14 -> 5120 | E15: =E11+E12+E13+E14 -> 5180
A16: Net profit (Rs) | B16: =B10-B11-B12-B13-B14 -> 2440 | C16: =C10-C11-C12-C13-C14 -> 9880 | D16: =D10-D11-D12-D13-D14 -> 9880 | E16: =E10-E11-E12-E13-E14 -> 17320
A17: Cumulative net (Rs) | B17: =B16 -> 2440 | C17: =B17+C16 -> 12320 | D17: =C17+D16 -> 22200 | E17: =D17+E16 -> 39520
A18: Cash remaining (Rs) | B18: =Assumptions!$B$18+B16 -> 102440 | C18: =B18+C16 -> 112320 | D18: =C18+D16 -> 122200 | E18: =D18+E16 -> 139520
A19: Per-active-dev payout (Rs) | B19: =IF(B6=0,0,B9/B6) -> 187.5 | C19: =IF(C6=0,0,C9/C6) -> 150 | D19: =IF(D6=0,0,D9/D6) -> 93.75 | E19: =IF(E6=0,0,E9/E6) -> 112.5

Sheet 14day_Sprint_Budget
A1: 14-Day Sprint — budget & targets
A3: Item | B3: Cost (Rs) | C3: Note
A4: Domain (devorix.ai) | B4: 1000 | C4: 1 yr
A5: Hosting (free tier to start) | B5: 0 | C5: Vercel/Render free
A6: Gemini API (AI tools, test) | B6: 1000 | C6: pay-as-you-go, tiny
A7: RazorpayX account | B7: 0 | C7: free to open; sandbox first
A8: Logo/landing polish (DIY) | B8: 0 | C8: use the AI Studio prototype
A9: Buffer | B9: 3000 | C9: misc
A10: TOTAL 14-day spend | B10: =SUM(B4:B9) -> 5000
A11: Cash left after sprint (of Rs1L) | B11: =Assumptions!$B$18-B10 -> 95000
A13: TARGETS (14 days): 1-2 advertisers on a 1-month paid pilot (Rs10-15k each); 50-100 installs; loop working end-to-end.

Sheet Compliance_CA
A1: Compliance reality (CA-grade) — stay lean now
A3: Item | B3: Now (<500 users) | C3: When it triggers / note
A4: Legal entity | B4: Proprietorship (no incorp.) | C4: Pvt Ltd later: ~Rs20k setup + Rs40-70k/yr. Defer until revenue proven.
A5: GST registration | B5: Not required | C5: Mandatory only above Rs20L/yr turnover (services). BUT advertisers may want a GST invoice for input credit -> may cost B2B deals; weigh per deal.
A6: GST rate on ad revenue | B6: n/a yet | C6: 18% (SAC 998361) once registered
A7: TDS on dev payouts | B7: Effectively none | C7: 194H 2% applies only >Rs20k/yr per person; your per-dev ~Rs1-2k/yr is far below. 194-O 1% only >Rs5L/yr. Collect PAN anyway.
A8: TDS YOU suffer (advertiser pays you) | B8: Maybe | C8: Advertiser (a business) may deduct 2% u/s 194C/194H on payments to you; claim as credit. Minor.
A9: Bank/payments | B9: Personal/current acct + RazorpayX | C9: UPI payouts Rs2-5+GST each; accrue to Rs500 threshold
A10: Annual compliance cost | B10: ~Rs0-5k | C10: ITR only as proprietor. Big jump to Rs40-70k/yr ONLY after Pvt Ltd.

Sheet Sources
A1: Sources & confidence (verified June 2026)
A3: Figure | B3: Value | C3: Confidence | D3: Source
A4: USD-INR | B4: 94.5 | C4: VERIFIED | D4: exchange-rates.org Jun 2026
A5: Real wait-state CPM | B5: $0.27-$11; steady ~$0.27 | C5: VERIFIED (self-reports) | D5: HN tester $4.43/407; PH reviewer $0.43/1587
A6: Advertiser demand / revenue | B6: None proven | C6: VERIFIED gap | D6: No public revenue/advertisers for Kickbacks; house ads only at launch
A7: Dev sentiment | B7: Cold/skeptical | C7: Med-High | D7: Show HN 2pts/0 comments; privacy & supply-chain objections dominant
A8: India dev display eCPM | B8: Rs64-130 ($0.7-1.4) | C8: ESTIMATE | D8: adcostly, apdigi (India tech niche)
A9: Pvt Ltd incorporation | B9: ~Rs20k one-time | C9: VERIFIED | D9: prakashaandco, registerkaro 2026
A10: GST on ads | B10: 18% (SAC 998361) | C10: VERIFIED | D10: busy.in / Razorpay
A11: GST threshold (services) | B11: Rs20L/yr | C11: VERIFIED | D11: CBIC
A12: TDS 194H / 194-O | B12: 2% / 1% | C12: VERIFIED rates | D12: incometaxindia.gov.in; thresholds Rs20k / Rs5L
A13: Annual compliance (Pvt Ltd) | B13: Rs40-70k/yr lean | C13: VERIFIED | D13: virtualauditor, incorpx
A14: RazorpayX UPI payout | B14: Rs2-5 +GST | C14: VERIFIED | D14: razorpay docs
A15: Installs/CPM/WAU in model | B15: various | C15: ASSUMPTION | D15: founder constraints + our estimates
