Workbook

Sheet Assumptions
A1: Devorix — Financial Model v3 (TIME-BASED)
A2: Impressions derived from coding HOURS x %wait-time (not prompts). Blue=input. Tags in Sources sheet.
A4: Parameter | B4: Value | C4: Note / Source
A5: USD -> INR | B5: =94.5 -> 94.5 | C5: VERIFIED Jun 2026
A6: Hours coding / day | B6: =6 -> 6 | C6: Founder: heavy vibe-coding user
A7: % of time AI is "thinking" (wait) | B7: =0.2 -> 0.2 | C7: VERIFIED-ish: tester 407 impr/3hr ~136/hr ~= 19% wait
A8: Seconds per impression | B8: =5 -> 5 | C8: 1 impression = 5s shown (Kickbacks unit)
A9: Active days / month | B9: =22 -> 22 | C9: assumption
A10: Gross CPM (INR / 1000 views) | B10: =95 -> 95 | C10: ~$1. Real range $0.27-$11; India dev display Rs64-130
A11: Fill rate (% views sold) | B11: =0.3 -> 0.3 | C11: THE constraint. Today ~0 (no advertisers). 30% = optimistic-but-earned
A12: Dev revenue share | B12: =0.5 -> 0.5 | C12: decided 50%
A13: Active developers | B13: =200 -> 200 | C13: 500 installs x 40% weekly-active
A14: Flat fee / advertiser / month (Rs) | B14: =15000 -> 15000 | C14: pilot sponsorship price
A15: # advertisers (flat) | B15: =2 -> 2 | C15: 14-day target 1-2
A16: Payout cost / txn (Rs) | B16: =4 -> 4 | C16: RazorpayX UPI Rs2-5 +GST
A17: Payout threshold (Rs) | B17: =500 -> 500 | C17: accrue + batch
A18: Infra + Gemini / month (Rs) | B18: =3000 -> 3000 | C18: hosting + AI tools
A19: Misc / month (Rs) | B19: =2000 -> 2000 | C19: domain, tools
A20: Founder salary / month (Rs) | B20: =0 -> 0 | C20: sweat equity
A21: Cash available (Rs) | B21: =100000 -> 100000 | C21: founder constraint
A23: --- GLOBAL EXPANSION INPUTS ---
A24: % of users that are foreign | B24: =0.2 -> 0.2 | C24: start small; ramp as payouts proven
A25: CPM foreign users (INR/1000) | B25: =472 -> 472 | C25: ~$5 conservative; observed $8-14 blog, $11 real
A26: Foreign payout cost (% of payout) | B26: =0.04 -> 0.04 | C26: Wise/PayPal ~3-5% +FX (vs UPI ~0.6%)
A27: Foreign payout threshold (Rs) | B27: =945 -> 945 | C27: ~$10 (Wise/PayPal min)

Sheet Per_Dev
A1: One developer — the time-based chain
A3: Step | B3: Value
A4: Ad-views / hour | B4: =3600*Assumptions!$B$7/Assumptions!$B$8 -> 144
A5: Ad-views / day | B5: =B4*Assumptions!$B$6 -> 864
A6: Ad-views / month | B6: =B5*Assumptions!$B$9 -> 19008
A7: Gross value / mo @100% fill (Rs) | B7: =B6/1000*Assumptions!$B$10 -> 1805.76
A8: Realized / mo (x fill rate) (Rs) | B8: =B7*Assumptions!$B$11 -> 541.728
A9: Dev keeps / month (Rs) | B9: =B8*Assumptions!$B$12 -> 270.864
A10: Dev keeps / day (Rs) | B10: =B9/Assumptions!$B$9 -> 12.312
A11: Platform keeps from this dev / mo (Rs) | B11: =B8*(1-Assumptions!$B$12) -> 270.864
A13: Key: ad-views are abundant. Earnings hinge on CPM x FILL. Today fill~0 => earnings~0.

Sheet Platform_Scale
A1: Platform monthly GROSS revenue (Rs) — active devs x fill rate
A2: At Gross CPM from Assumptions. Shows supply is huge; value depends on fill (demand).
A4: Active devs \ fill | B4: 5% fill | C4: 15% fill | D4: 30% fill | E4: 50% fill | F4: 100% fill
A5: 50 | B5: =A5*(3600*Assumptions!$B$7/Assumptions!$B$8*Assumptions!$B$6*Assumptions!$B$9)/1000*Assumptions!$B$10*0.05 -> 4514.4 | C5: =A5*(3600*Assumptions!$B$7/Assumptions!$B$8*Assumptions!$B$6*Assumptions!$B$9)/1000*Assumptions!$B$10*0.15 -> 13543.2 | D5: =A5*(3600*Assumptions!$B$7/Assumptions!$B$8*Assumptions!$B$6*Assumptions!$B$9)/1000*Assumptions!$B$10*0.3 -> 27086.4 | E5: =A5*(3600*Assumptions!$B$7/Assumptions!$B$8*Assumptions!$B$6*Assumptions!$B$9)/1000*Assumptions!$B$10*0.5 -> 45144 | F5: =A5*(3600*Assumptions!$B$7/Assumptions!$B$8*Assumptions!$B$6*Assumptions!$B$9)/1000*Assumptions!$B$10*1 -> 90288
A6: 100 | B6: =A6*(3600*Assumptions!$B$7/Assumptions!$B$8*Assumptions!$B$6*Assumptions!$B$9)/1000*Assumptions!$B$10*0.05 -> 9028.8 | C6: =A6*(3600*Assumptions!$B$7/Assumptions!$B$8*Assumptions!$B$6*Assumptions!$B$9)/1000*Assumptions!$B$10*0.15 -> 27086.4 | D6: =A6*(3600*Assumptions!$B$7/Assumptions!$B$8*Assumptions!$B$6*Assumptions!$B$9)/1000*Assumptions!$B$10*0.3 -> 54172.8 | E6: =A6*(3600*Assumptions!$B$7/Assumptions!$B$8*Assumptions!$B$6*Assumptions!$B$9)/1000*Assumptions!$B$10*0.5 -> 90288 | F6: =A6*(3600*Assumptions!$B$7/Assumptions!$B$8*Assumptions!$B$6*Assumptions!$B$9)/1000*Assumptions!$B$10*1 -> 180576
A7: 200 | B7: =A7*(3600*Assumptions!$B$7/Assumptions!$B$8*Assumptions!$B$6*Assumptions!$B$9)/1000*Assumptions!$B$10*0.05 -> 18057.6 | C7: =A7*(3600*Assumptions!$B$7/Assumptions!$B$8*Assumptions!$B$6*Assumptions!$B$9)/1000*Assumptions!$B$10*0.15 -> 54172.8 | D7: =A7*(3600*Assumptions!$B$7/Assumptions!$B$8*Assumptions!$B$6*Assumptions!$B$9)/1000*Assumptions!$B$10*0.3 -> 108345.6 | E7: =A7*(3600*Assumptions!$B$7/Assumptions!$B$8*Assumptions!$B$6*Assumptions!$B$9)/1000*Assumptions!$B$10*0.5 -> 180576 | F7: =A7*(3600*Assumptions!$B$7/Assumptions!$B$8*Assumptions!$B$6*Assumptions!$B$9)/1000*Assumptions!$B$10*1 -> 361152
A8: 350 | B8: =A8*(3600*Assumptions!$B$7/Assumptions!$B$8*Assumptions!$B$6*Assumptions!$B$9)/1000*Assumptions!$B$10*0.05 -> 31600.8 | C8: =A8*(3600*Assumptions!$B$7/Assumptions!$B$8*Assumptions!$B$6*Assumptions!$B$9)/1000*Assumptions!$B$10*0.15 -> 94802.4 | D8: =A8*(3600*Assumptions!$B$7/Assumptions!$B$8*Assumptions!$B$6*Assumptions!$B$9)/1000*Assumptions!$B$10*0.3 -> 189604.8 | E8: =A8*(3600*Assumptions!$B$7/Assumptions!$B$8*Assumptions!$B$6*Assumptions!$B$9)/1000*Assumptions!$B$10*0.5 -> 316008 | F8: =A8*(3600*Assumptions!$B$7/Assumptions!$B$8*Assumptions!$B$6*Assumptions!$B$9)/1000*Assumptions!$B$10*1 -> 632016
A9: 500 | B9: =A9*(3600*Assumptions!$B$7/Assumptions!$B$8*Assumptions!$B$6*Assumptions!$B$9)/1000*Assumptions!$B$10*0.05 -> 45144 | C9: =A9*(3600*Assumptions!$B$7/Assumptions!$B$8*Assumptions!$B$6*Assumptions!$B$9)/1000*Assumptions!$B$10*0.15 -> 135432 | D9: =A9*(3600*Assumptions!$B$7/Assumptions!$B$8*Assumptions!$B$6*Assumptions!$B$9)/1000*Assumptions!$B$10*0.3 -> 270864 | E9: =A9*(3600*Assumptions!$B$7/Assumptions!$B$8*Assumptions!$B$6*Assumptions!$B$9)/1000*Assumptions!$B$10*0.5 -> 451440 | F9: =A9*(3600*Assumptions!$B$7/Assumptions!$B$8*Assumptions!$B$6*Assumptions!$B$9)/1000*Assumptions!$B$10*1 -> 902880
A12: Your MARGIN = above x (1 - dev share). At 50% share, halve these numbers.

Sheet CPM_vs_FlatDeal
A1: CPM vs Flat deal — same audience, two ways to sell
A2: At current Assumptions (active devs, CPM, fill, flat fee, #advertisers).
A4: Metric | B4: Flat deal | C4: CPM deal
A5: Total ad-views / month | B5: =Assumptions!$B$13*(3600*Assumptions!$B$7/Assumptions!$B$8*Assumptions!$B$6*Assumptions!$B$9) -> 3801600 | C5: =Assumptions!$B$13*(3600*Assumptions!$B$7/Assumptions!$B$8*Assumptions!$B$6*Assumptions!$B$9) -> 3801600
A6: Revenue / month (Rs) | B6: =Assumptions!$B$15*Assumptions!$B$14 -> 30000 | C6: =B5*Assumptions!$B$11/1000*Assumptions!$B$10 -> 108345.6
A7: Implied eCPM (Rs / 1000 views) | B7: =B6/(B5/1000) -> 7.8914141 | C7: =Assumptions!$B$10*Assumptions!$B$11 -> 28.5
A8: Dev pool / month (Rs) | B8: =B6*Assumptions!$B$12 -> 15000 | C8: =C6*Assumptions!$B$12 -> 54172.8
A9: Per active dev / month (Rs) | B9: =B8/Assumptions!$B$13 -> 75 | C9: =C8/Assumptions!$B$13 -> 270.864
A10: Your margin / month (Rs) | B10: =B6*(1-Assumptions!$B$12) -> 15000 | C10: =C6*(1-Assumptions!$B$12) -> 54172.8
A12: Takeaway: flat deal = easy 1st sale but you sell cheap (low eCPM). CPM scales with usage+demand.

Sheet Plan_4mo
A1: 4-Month Plan (flat deals, time-based audience)
A4: Metric | B4: Month 1 | C4: Month 2 | D4: Month 3 | E4: Month 4
A5: Installs (cumulative) | B5: 100 | C5: 250 | D5: 400 | E5: 500
A6: Active devs (x40%) | B6: =B5*0.4 -> 40 | C6: =C5*0.4 -> 100 | D6: =D5*0.4 -> 160 | E6: =E5*0.4 -> 200
A7: Ad-views available / mo | B7: =B6*(3600*Assumptions!$B$7/Assumptions!$B$8*Assumptions!$B$6*Assumptions!$B$9) -> 760320 | C7: =C6*(3600*Assumptions!$B$7/Assumptions!$B$8*Assumptions!$B$6*Assumptions!$B$9) -> 1900800 | D7: =D6*(3600*Assumptions!$B$7/Assumptions!$B$8*Assumptions!$B$6*Assumptions!$B$9) -> 3041280 | E7: =E6*(3600*Assumptions!$B$7/Assumptions!$B$8*Assumptions!$B$6*Assumptions!$B$9) -> 3801600
A8: # Advertisers (flat) | B8: 1 | C8: 2 | D8: 2 | E8: 3
A9: Revenue (Rs) | B9: =B8*Assumptions!$B$14 -> 15000 | C9: =C8*Assumptions!$B$14 -> 30000 | D9: =D8*Assumptions!$B$14 -> 30000 | E9: =E8*Assumptions!$B$14 -> 45000
A10: Implied eCPM (Rs) | B10: =IF(B7=0,0,B9/(B7/1000)) -> 19.728535 | C10: =IF(C7=0,0,C9/(C7/1000)) -> 15.782828 | D10: =IF(D7=0,0,D9/(D7/1000)) -> 9.8642677 | E10: =IF(E7=0,0,E9/(E7/1000)) -> 11.837121
A11: Dev pool (Rs) | B11: =B9*Assumptions!$B$12 -> 7500 | C11: =C9*Assumptions!$B$12 -> 15000 | D11: =D9*Assumptions!$B$12 -> 15000 | E11: =E9*Assumptions!$B$12 -> 22500
A12: Platform margin (Rs) | B12: =B9*(1-Assumptions!$B$12) -> 7500 | C12: =C9*(1-Assumptions!$B$12) -> 15000 | D12: =D9*(1-Assumptions!$B$12) -> 15000 | E12: =E9*(1-Assumptions!$B$12) -> 22500
A13: Payout cost (Rs) | B13: =IF(B11=0,0,B11/Assumptions!$B$17*Assumptions!$B$16) -> 60 | C13: =IF(C11=0,0,C11/Assumptions!$B$17*Assumptions!$B$16) -> 120 | D13: =IF(D11=0,0,D11/Assumptions!$B$17*Assumptions!$B$16) -> 120 | E13: =IF(E11=0,0,E11/Assumptions!$B$17*Assumptions!$B$16) -> 180
A14: Fixed costs (Rs) | B14: =Assumptions!$B$18+Assumptions!$B$19+Assumptions!$B$20 -> 5000 | C14: =Assumptions!$B$18+Assumptions!$B$19+Assumptions!$B$20 -> 5000 | D14: =Assumptions!$B$18+Assumptions!$B$19+Assumptions!$B$20 -> 5000 | E14: =Assumptions!$B$18+Assumptions!$B$19+Assumptions!$B$20 -> 5000
A15: Net profit (Rs) | B15: =B12-B13-B14 -> 2440 | C15: =C12-C13-C14 -> 9880 | D15: =D12-D13-D14 -> 9880 | E15: =E12-E13-E14 -> 17320
A16: Cumulative net (Rs) | B16: =B15 -> 2440 | C16: =B16+C15 -> 12320 | D16: =C16+D15 -> 22200 | E16: =D16+E15 -> 39520
A17: Cash remaining (Rs) | B17: =Assumptions!$B$21+B15 -> 102440 | C17: =B17+C15 -> 112320 | D17: =C17+D15 -> 122200 | E17: =D17+E15 -> 139520
A18: Per active dev (Rs) | B18: =IF(B6=0,0,B11/B6) -> 187.5 | C18: =IF(C6=0,0,C11/C6) -> 150 | D18: =IF(D6=0,0,D11/D6) -> 93.75 | E18: =IF(E6=0,0,E11/E6) -> 112.5

Sheet 14day_Sprint
A1: 14-Day Sprint — budget & targets
A3: Item | B3: Cost (Rs) | C3: Note
A4: Domain | B4: 1000 | C4: 1 yr
A5: Hosting | B5: 0 | C5: free tier
A6: Gemini API (test) | B6: 1000 | C6: tiny
A7: RazorpayX | B7: 0 | C7: free; sandbox first
A8: Landing (reuse prototype) | B8: 0 | C8: AI Studio app
A9: Buffer | B9: 3000 | C9: misc
A10: TOTAL spend | B10: =SUM(B4:B9) -> 5000
A11: Cash left (of Rs1L) | B11: =Assumptions!$B$21-B10 -> 95000
A13: TARGETS: 1-2 advertisers (Rs10-15k pilot); 50-100 installs; loop works end-to-end.

Sheet Compliance_CA
A1: Compliance reality (CA-grade) — stay lean
A3: Item | B3: Now (<500 users) | C3: Trigger / note
A4: Entity | B4: Proprietorship | C4: Pvt Ltd later: ~Rs20k + Rs40-70k/yr. Defer.
A5: GST | B5: Not required | C5: Mandatory >Rs20L/yr. Advertiser may want GST invoice -> weigh per deal.
A6: GST rate on ads | B6: n/a yet | C6: 18% (SAC 998361) once registered
A7: TDS on dev payouts | B7: ~None | C7: 194H 2% only >Rs20k/yr per person; you pay ~Rs1-2k. Collect PAN.
A8: Payouts | B8: RazorpayX UPI | C8: Rs2-5+GST each; batch at Rs500
A9: Annual compliance | B9: ~Rs0-5k | C9: ITR only as proprietor; jumps after Pvt Ltd
A11: --- GOING GLOBAL (confirm with CA) ---
A12: Billing foreign advertisers | B12: Export of services | C12: Zero-rated GST WITH LUT; but register GST + file LUT to claim it. Need FIRC/receipt for each USD inflow (FEMA).
A13: Receiving USD | B13: PayPal / Wise / Razorpay Intl | C13: FX + fees; keep FIRC/FIRA as export proof
A14: Paying foreign developers | B14: Wise / PayPal | C14: No UPI abroad; ~3-5% cost; Sec 195 withholding on non-residents may apply unless treaty/no-PE — CONFIRM with CA
A15: Entity for scale | B15: Pvt Ltd likely needed | C15: Foreign clients/investors prefer it; revisit once revenue real

Sheet Sources
A1: Sources & confidence (verified Jun 2026)
A3: Figure | B3: Value | C3: Confidence | D3: Source
A4: USD-INR | B4: 94.5 | C4: VERIFIED | D4: exchange-rates.org
A5: Impr/hour (agentic) | B5: ~136/hr | C5: VERIFIED self-report | D5: HN tester 407/3hr
A6: Real CPM | B6: $0.27-$11; steady ~$0.27 | C6: VERIFIED | D6: HN/PH self-reports
A7: Advertiser demand | B7: None proven | C7: VERIFIED gap | D7: no public revenue/advertisers
A8: India dev display eCPM | B8: Rs64-130 | C8: ESTIMATE | D8: adcostly/apdigi
A9: Pvt Ltd setup | B9: ~Rs20k | C9: VERIFIED | D9: prakashaandco 2026
A10: GST on ads / threshold | B10: 18% / Rs20L | C10: VERIFIED | D10: busy.in / CBIC
A11: TDS 194H/194-O | B11: 2% / 1% | C11: VERIFIED rates | D11: incometaxindia.gov.in
A12: Pvt Ltd annual compliance | B12: Rs40-70k/yr | C12: VERIFIED | D12: virtualauditor
A13: UPI payout cost | B13: Rs2-5+GST | C13: VERIFIED | D13: razorpay docs
A14: Hours, wait%, fill, CPM | B14: model inputs | C14: ASSUMPTION | D14: founder + our estimates
... A19: Wise/PayPal payout cost | B19: ~3-5% +FX | C19: ESTIMATE | D19: provider pricing

Sheet Global_Blended
A1: Global / blended — adding foreign users & advertisers
A2: Foreign impressions pay ~5x India. Driven by Assumptions (% foreign, CPM foreign, fill).
A4: Metric | B4: Value
A5: Active users (total) | B5: =Assumptions!$B$13 -> 200
A6: India users | B6: =B5*(1-Assumptions!$B$24) -> 160
A7: Foreign users | B7: =B5*Assumptions!$B$24 -> 40
A8: Ad-views / user / month | B8: =(3600*Assumptions!$B$7/Assumptions!$B$8*Assumptions!$B$6*Assumptions!$B$9) -> 19008
A9: India revenue / mo (Rs) | B9: =B6*B8/1000*Assumptions!$B$10*Assumptions!$B$11 -> 86676.48
A10: Foreign revenue / mo (Rs) | B10: =B7*B8/1000*Assumptions!$B$25*Assumptions!$B$11 -> 107661.31
A11: TOTAL revenue / mo (Rs) | B11: =B9+B10 -> 194337.79
A12: India-only revenue (same users) (Rs) | B12: =B5*B8/1000*Assumptions!$B$10*Assumptions!$B$11 -> 108345.6
A13: Uplift from going global (x) | B13: =B11/B12 -> 1.7936842
A14: Blended eCPM (Rs/1000) | B14: =B11/((B5*B8)/1000) -> 51.12
A15: Dev pool / mo (Rs) | B15: =B11*Assumptions!$B$12 -> 97168.896
A16: less foreign payout cost (Rs) | B16: =B10*Assumptions!$B$12*Assumptions!$B$26 -> 2153.2262
A17: Platform margin / mo (Rs) | B17: =B11*(1-Assumptions!$B$12)-B16 -> 95015.67
A19: Takeaway: ~20% foreign users can ~2x revenue (foreign CPM ~5x). Payout cost rises but stays small.
